pydebuggerupgrade/__init__.py
pydebuggerupgrade/__main__.py
pydebuggerupgrade/artifactprovider.py
pydebuggerupgrade/backend.py
pydebuggerupgrade/dfuprotocol.py
pydebuggerupgrade/flipprogrammer.py
pydebuggerupgrade/flipprotocol.py
pydebuggerupgrade/hexutils.py
pydebuggerupgrade/logging.yaml
pydebuggerupgrade/pydebuggerupgrade.py
pydebuggerupgrade/pydebuggerupgrade_errors.py
pydebuggerupgrade/pydebuggerupgrade_main.py
pydebuggerupgrade/supported_tools.py
pydebuggerupgrade/upgrader.py
pydebuggerupgrade/version.py
pydebuggerupgrade/tests/__init__.py
pydebuggerupgrade/tests/test_artifactprovider.py
pydebuggerupgrade/tests/test_backend.py
pydebuggerupgrade/tests/test_flipprogrammer.py
pydebuggerupgrade/tests/test_flipprotocol.py
pydebuggerupgrade-3.7.1.60.dist-info/LICENSE.txt
pydebuggerupgrade-3.7.1.60.dist-info/METADATA
pydebuggerupgrade-3.7.1.60.dist-info/WHEEL
pydebuggerupgrade-3.7.1.60.dist-info/entry_points.txt
pydebuggerupgrade-3.7.1.60.dist-info/top_level.txt
pydebuggerupgrade-3.7.1.60.dist-info/RECORD
