Metadata-Version: 2.1
Name: pydebuggerupgrade
Version: 3.7.1.60
Summary: CLI and library utility for upgrading firmware on Microchip PKOB nano (nEDBG) debugger
Home-page: http://www.microchip.com
Author: Microchip Technology
Author-email: support@microchip.com
License: MIT
Platform: UNKNOWN
Classifier: Development Status :: 4 - Beta
Classifier: Intended Audience :: Developers
Classifier: Topic :: Software Development :: Embedded Systems
Classifier: License :: OSI Approved :: MIT License
Classifier: Programming Language :: Python :: 3
Classifier: Programming Language :: Python :: 3.6
Classifier: Programming Language :: Python :: 3.7
Classifier: Programming Language :: Python :: 3.8
Classifier: Programming Language :: Python :: 3.9
Classifier: Operating System :: Microsoft :: Windows
Classifier: Operating System :: POSIX :: Linux
Classifier: Operating System :: MacOS
Requires-Dist: pyusb
Requires-Dist: IntelHex
Requires-Dist: requests
Requires-Dist: packaging
Requires-Dist: pyedbglib (>=2.3)
Requires-Dist: PyYAML
Requires-Dist: appdirs
Requires-Dist: pathlib2 ; python_version < "3"
Provides-Extra: dev
Requires-Dist: pylint ; extra == 'dev'
Requires-Dist: parameterized ; extra == 'dev'
Requires-Dist: pytest ; extra == 'dev'
Requires-Dist: mock ; extra == 'dev'
Provides-Extra: test
Requires-Dist: parameterized ; extra == 'test'
Requires-Dist: pytest ; extra == 'test'
Requires-Dist: mock ; extra == 'test'
